{
  "type": "object",
  "properties": {
    "versionNumber": {
      "type": [
        "null",
        "integer"
      ]
    },
    "versionId": {
      "type": [
        "null",
        "integer"
      ]
    },
    "latestDraftVersionNumber": {
      "type": [
        "null",
        "integer"
      ]
    },
    "publishedNumber": {
      "type": [
        "null",
        "integer"
      ]
    },
    "publishedAt": {
      "anyOf": [
        {
          "type": "null"
        },
        {
          "format": "date-time",
          "type": "string"
        }
      ]
    },
    "hasUnpublishedChanges": {
      "type": [
        "null",
        "boolean"
      ]
    },
    "id": {
      "type": "integer"
    },
    "eid": {
      "type": [
        "null",
        "string"
      ]
    },
    "slug": {
      "type": [
        "null",
        "string"
      ]
    },
    "name": {
      "type": [
        "null",
        "string"
      ]
    },
    "visibility": {
      "type": [
        "null",
        "string"
      ]
    },
    "config": {
      "type": [
        "null",
        "object"
      ]
    },
    "hasSigners": {
      "type": [
        "null",
        "boolean"
      ]
    },
    "signatureProviderType": {
      "type": [
        "null",
        "string"
      ]
    },
    "availableSignatureProviderTypes": {
      "type": [
        "null",
        "array"
      ]
    },
    "remainingSubmissions": {
      "type": [
        "null",
        "object"
      ]
    },
    "createdAt": {
      "type": [
        "null",
        "object"
      ]
    },
    "updatedAt": {
      "type": [
        "null",
        "object"
      ]
    },
    "archivedAt": {
      "type": [
        "null",
        "object"
      ]
    },
    "expiresAt": {
      "type": [
        "null",
        "object"
      ]
    },
    "organizationSlug": {
      "type": [
        "null",
        "string"
      ]
    }
  }
}
